image_metadata_recorder/__init__.py
image_metadata_recorder/cli.py
image_metadata_recorder/extractors/__init__.py
image_metadata_recorder/extractors/czi_extractor.py
image_metadata_recorder/extractors/tiff_extractor.py
image_metadata_recorder/processors/__init__.py
image_metadata_recorder/processors/standard_processor.py
image_metadata_recorder/reporters/__init__.py
image_metadata_recorder/reporters/keypath_util.py
image_metadata_recorder/reporters/markdown_reporter.py
image_metadata_recorder/reporters/structure_reporter.py
image_metadata_recorder/workflow/__init__.py
image_metadata_recorder/workflow/context.py
image_metadata_recorder/workflow/workflow.py
image_metadata_recorder-1.4.0.dist-info/METADATA
image_metadata_recorder-1.4.0.dist-info/WHEEL
image_metadata_recorder-1.4.0.dist-info/entry_points.txt
image_metadata_recorder-1.4.0.dist-info/top_level.txt
image_metadata_recorder-1.4.0.dist-info/RECORD
