Metadata-Version: 2.4
Name: image-metadata-recorder
Version: 1.4.0
Summary: A tool to extract, analyze, and report on metadata from TIFF, QPTIFF, and CZI files.
Author-email: Saptarshi Chakrabarti <saptarshi.chakrabarti@kuleuven.be>
License: MIT
Project-URL: Homepage, https://github.com/saptarshichakrabarti/image-metadata-recorder
Project-URL: Documentation, https://github.com/saptarshichakrabarti/image-metadata-recorder#readme
Project-URL: Repository, https://github.com/saptarshichakrabarti/image-metadata-recorder.git
Project-URL: Issues, https://github.com/saptarshichakrabarti/image-metadata-recorder/issues
Classifier: Development Status :: 4 - Beta
Classifier: Programming Language :: Python :: 3
Classifier: Programming Language :: Python :: 3.8
Classifier: Programming Language :: Python :: 3.9
Classifier: Programming Language :: Python :: 3.10
Classifier: License :: OSI Approved :: MIT License
Classifier: Operating System :: OS Independent
Classifier: Topic :: Scientific/Engineering :: Bio-Informatics
Classifier: Topic :: Scientific/Engineering :: Medical Science Apps.
Classifier: Topic :: Utilities
Classifier: Intended Audience :: Science/Research
Classifier: Intended Audience :: Healthcare Industry
Requires-Python: >=3.8
Requires-Dist: tifffile>=2023.0.0
Requires-Dist: aicspylibczi>=3.0.0
Requires-Dist: xmltodict>=0.13.0
Provides-Extra: dev
Requires-Dist: pytest>=7.0.0; extra == "dev"
Requires-Dist: black>=22.0.0; extra == "dev"
Requires-Dist: isort>=5.0.0; extra == "dev"
Requires-Dist: mypy>=1.0.0; extra == "dev"
Requires-Dist: flake8>=6.0.0; extra == "dev"
